frosted/settings.py
frosted/main.py
frosted/messages.py
frosted/checker.py
frosted/api.py
frosted/__init__.py
frosted/reporter.py
frosted/test/test_api.py
frosted/test/utils.py
frosted/test/test_return_with_arguments_inside_generator.py
frosted/test/test_imports.py
frosted/test/test_noqa.py
frosted/test/test_other.py
frosted/test/test_function_calls.py
frosted/test/test_script.py
frosted/test/__init__.py
frosted/test/test_doctests.py
frosted/test/test_undefined_names.py
frosted-1.4.1.data/scripts/frosted
frosted-1.4.1.dist-info/top_level.txt
frosted-1.4.1.dist-info/DESCRIPTION.rst
frosted-1.4.1.dist-info/RECORD
frosted-1.4.1.dist-info/WHEEL
frosted-1.4.1.dist-info/pydist.json
frosted-1.4.1.dist-info/METADATA
frosted-1.4.1.dist-info/entry_points.txt
